cnsir/__init__.py
cnsir/api.py
cnsir/config/settings.yaml
cnsir/metadata/id_information.yaml
cnsir/metadata/raw_files.yaml
cnsir/metadata/schema.yaml
cnsir/metadata/tables.yaml
cnsir-0.1.11.dist-info/METADATA
cnsir-0.1.11.dist-info/WHEEL
cnsir-0.1.11.dist-info/RECORD
