Metadata-Version: 2.1
Name: cnsir
Version: 0.1.11
Summary: 
Author: mohammad amin alavian
Author-email: m.amin.alavian@gmail.com
Requires-Python: >=3.10
Classifier: Programming Language :: Python :: 3
Classifier: Programming Language :: Python :: 3.10
Classifier: Programming Language :: Python :: 3.11
Classifier: Programming Language :: Python :: 3.12
Requires-Dist: bssir (==0.3.7)
